searvey/__init__.py
searvey/_chs_api.py
searvey/_common.py
searvey/_coops_api.py
searvey/_ioc_api.py
searvey/_ndbc_api.py
searvey/coops.py
searvey/critech.py
searvey/custom_types.py
searvey/erddap.py
searvey/ioc.py
searvey/models.py
searvey/multi.py
searvey/rate_limit.py
searvey/stations.py
searvey/uhslc.py
searvey/us_states.json
searvey/usgs.py
searvey/utils.py
searvey-0.3.17.dist-info/METADATA
searvey-0.3.17.dist-info/WHEEL
searvey-0.3.17.dist-info/licenses/LICENSE
searvey-0.3.17.dist-info/RECORD
