Metadata-Version: 2.4
Name: searvey
Version: 0.3.17
Summary: Sea state observational data retrieval
License: GPL-3.0-or-later
License-File: LICENSE
Author: Panos Mavrogiorgos
Author-email: pmav99@gmail.com
Requires-Python: >=3.9,<4.0
Classifier: Development Status :: 4 - Beta
Classifier: Environment :: Other Environment
Classifier: Intended Audience :: Developers
Classifier: Intended Audience :: Science/Research
Classifier: License :: OSI Approved :: GNU General Public License v3 or later (GPLv3+)
Classifier: Operating System :: OS Independent
Classifier: Programming Language :: Python
Classifier: Programming Language :: Python :: 3
Classifier: Programming Language :: Python :: 3.9
Classifier: Programming Language :: Python :: 3.10
Classifier: Programming Language :: Python :: 3.11
Classifier: Programming Language :: Python :: 3.12
Classifier: Programming Language :: Python :: 3.13
Classifier: Programming Language :: Python :: 3.14
Classifier: Topic :: Scientific/Engineering :: Atmospheric Science
Classifier: Topic :: Scientific/Engineering :: Hydrology
Requires-Dist: Shapely
Requires-Dist: beautifulsoup4
Requires-Dist: dataretrieval (>=1)
Requires-Dist: deprecated
Requires-Dist: erddapy
Requires-Dist: geopandas
Requires-Dist: html5lib
Requires-Dist: httpx
Requires-Dist: limits
Requires-Dist: lxml[html-clean]
Requires-Dist: multifutures
Requires-Dist: ndbc-api (==0.24.1.6.1)
Requires-Dist: numpy
Requires-Dist: pandas
Requires-Dist: pydantic (>2)
Requires-Dist: requests
Requires-Dist: tenacity (!=8.4.0)
Requires-Dist: tqdm
Requires-Dist: typing-extensions
Requires-Dist: xarray
Project-URL: Repository, https://github.com/oceanmodeling/searvey.git
